MANIFEST.in
README.rst
setup.cfg
setup.py
lymph/__init__.py
lymph/sqlalchemy/__init__.py
lymph/sqlalchemy/base.py
lymph/sqlalchemy/columns.py
lymph/sqlalchemy/interfaces.py
lymph/sqlalchemy/store.py
lymph/sqlalchemy/testing.py
lymph/sqlalchemy/utils.py
lymph/sqlalchemy/cli/__init__.py
lymph/sqlalchemy/cli/init_db.py
lymph/sqlalchemy/cli/migrate.py
lymph/sqlalchemy/cli/shell.py
lymph/sqlalchemy/migrations/__init__.py
lymph/sqlalchemy/migrations/templates/generic/alembic.ini.mako
lymph/sqlalchemy/migrations/templates/generic/script.py.mako
lymph/sqlalchemy/migrations/templates/geoalchemy/alembic.ini.mako
lymph/sqlalchemy/migrations/templates/geoalchemy/script.py.mako
lymph/sqlalchemy/tests/__init__.py
lymph/sqlalchemy/tests/test_autoincrement.py
lymph/sqlalchemy/tests/test_sqlalchemy.py
lymph_sqlalchemy.egg-info/PKG-INFO
lymph_sqlalchemy.egg-info/SOURCES.txt
lymph_sqlalchemy.egg-info/dependency_links.txt
lymph_sqlalchemy.egg-info/entry_points.txt
lymph_sqlalchemy.egg-info/namespace_packages.txt
lymph_sqlalchemy.egg-info/requires.txt
lymph_sqlalchemy.egg-info/top_level.txt
requirements/base.txt
requirements/dev.txt
requirements/docs.txt