Metadata-Version: 1.0
Name: lymph-sqlalchemy
Version: 0.6.0
Summary: UNKNOWN
Home-page: http://github.com/deliveryhero/lymph-sqlalchemy/
Author: Dushyant Rijhwani
Author-email: dushyant.rijhwani@deliveryhero.com
License: Apache License (2.0)
Platform: UNKNOWN
